propsettings_qt/__init__.py
propsettings_qt/setting_widget_retrieval.py
propsettings_qt/ui_settings_area.py
propsettings_qt/object_drawers/__init__.py
propsettings_qt/object_drawers/default_drawer.py
propsettings_qt/object_drawers/object_drawer.py
propsettings_qt/setting_drawers/__init__.py
propsettings_qt/setting_drawers/bool_setting_drawer.py
propsettings_qt/setting_drawers/list_setting_drawer.py
propsettings_qt/setting_drawers/object_setting_drawer.py
propsettings_qt/setting_drawers/path_setting_drawer.py
propsettings_qt/setting_drawers/range_setting_drawer.py
propsettings_qt/setting_drawers/selectable_setting_drawer.py
propsettings_qt/setting_drawers/setting_drawer.py
propsettings_qt/setting_drawers/text_setting_drawer.py
propsettings_qt/widgets/__init__.py
propsettings_qt/widgets/float_slider.py
propsettings_qt-0.2.8.dist-info/LICENSE
propsettings_qt-0.2.8.dist-info/METADATA
propsettings_qt-0.2.8.dist-info/WHEEL
propsettings_qt-0.2.8.dist-info/top_level.txt
propsettings_qt-0.2.8.dist-info/RECORD
