Metadata-Version: 2.1
Name: propsettings-qt
Version: 0.2.8
Summary: Provides automatic widget generation for editing member variables of an object.
Home-page: https://github.com/mnicolas94/propsettings_qt
Author: Miguel Nicolás-Díaz
Author-email: miguelcok27@gmail.com
License: UNKNOWN
Platform: UNKNOWN
Classifier: Programming Language :: Python :: 3
Classifier: License :: OSI Approved :: MIT License
Classifier: Operating System :: OS Independent
Classifier: Development Status :: 3 - Alpha
Classifier: Intended Audience :: Developers
Requires-Python: >=3.6
License-File: LICENSE
Requires-Dist: propsettings (>=0.1.15)
Requires-Dist: PySide2
